chatkit/__init__.py
chatkit/actions.py
chatkit/agents.py
chatkit/errors.py
chatkit/icons.py
chatkit/logger.py
chatkit/py.typed
chatkit/server.py
chatkit/store.py
chatkit/types.py
chatkit/version.py
chatkit/widgets.py
openai_chatkit-1.5.2.dist-info/licenses/LICENSE
openai_chatkit-1.5.2.dist-info/licenses/NOTICE
openai_chatkit-1.5.2.dist-info/METADATA
openai_chatkit-1.5.2.dist-info/WHEEL
openai_chatkit-1.5.2.dist-info/top_level.txt
openai_chatkit-1.5.2.dist-info/RECORD
